xml2xlsx/__init__.py
xml2xlsx/command_line.py
xml2xlsx-1.0.2.dist-info/METADATA
xml2xlsx-1.0.2.dist-info/WHEEL
xml2xlsx-1.0.2.dist-info/entry_points.txt
xml2xlsx-1.0.2.dist-info/top_level.txt
xml2xlsx-1.0.2.dist-info/RECORD
