Metadata-Version: 2.1
Name: xml2xlsx
Version: 1.0.2
Summary: XML to XLSX converter
Home-page: https://github.com/marrog/xml2xlsx
Author: Piotr Kaczyński
Author-email: pkaczyns@gmail.com
License: MIT
Keywords: xml lxml xlsx development
Platform: UNKNOWN
Classifier: Development Status :: 5 - Production/Stable
Classifier: Intended Audience :: Developers
Classifier: Topic :: Software Development :: Build Tools
Classifier: License :: OSI Approved :: MIT License
Classifier: Programming Language :: Python :: 2.7
Classifier: Programming Language :: Python :: 3
Classifier: Programming Language :: Python :: 3.5
Classifier: Programming Language :: Python :: 3.6
Requires-Dist: lxml (>=3.6)
Requires-Dist: openpyxl (<2.5,>=2.4.7)
Requires-Dist: six (>=1.10)
